steppyngstounes/__init__.py
steppyngstounes/checkpointStepper.py
steppyngstounes/fixedStepper.py
steppyngstounes/parsimoniousStepper.py
steppyngstounes/pidStepper.py
steppyngstounes/pseudoRKQSStepper.py
steppyngstounes/scaledStepper.py
steppyngstounes/sequenceStepper.py
steppyngstounes/stepper.py
steppyngstounes-0.1.1.dist-info/licenses/LICENSE.rst
steppyngstounes-0.1.1.dist-info/METADATA
steppyngstounes-0.1.1.dist-info/WHEEL
steppyngstounes-0.1.1.dist-info/top_level.txt
steppyngstounes-0.1.1.dist-info/RECORD
