Metadata-Version: 2.4
Name: steppyngstounes
Version: 0.1.1
Summary: A package of iterators for advancing from start to stop
Home-page: https://github.com/guyer/steppyngstounes
Author: Jonathan E. Guyer
Author-email: guyer@nist.gov
License: NIST Public Domain
Classifier: Programming Language :: Python :: 2.7
Classifier: Programming Language :: Python :: 3
Classifier: Intended Audience :: Science/Research
Classifier: License :: Public Domain
Classifier: Natural Language :: English
Classifier: Operating System :: OS Independent
Requires-Python: >=2.7, <4
License-File: LICENSE.rst
Requires-Dist: numpy
Requires-Dist: scipy
Dynamic: author
Dynamic: author-email
Dynamic: classifier
Dynamic: description
Dynamic: description-content-type
Dynamic: home-page
Dynamic: license
Dynamic: license-file
Dynamic: requires-dist
Dynamic: requires-python
Dynamic: summary
